confu/__init__.py
confu/ansible.py
confu/aws.py
confu/cfn.py
confu/cli.py
confu/pkg.py
confu/settings.py
confu/shell/__init__.py
py3_con_fu-0.2.2.data/scripts/confu
py3_con_fu-0.2.2.dist-info/LICENSE
py3_con_fu-0.2.2.dist-info/METADATA
py3_con_fu-0.2.2.dist-info/WHEEL
py3_con_fu-0.2.2.dist-info/top_level.txt
py3_con_fu-0.2.2.dist-info/RECORD
