Metadata-Version: 2.1
Name: py3-con-fu
Version: 0.2.2
Summary: Fu for con.
Home-page: https://github.com/bninja/confu
Author: Egon Spengler
Author-email: egon@gb.com
License: BSD
Platform: any
Classifier: Intended Audience :: Developers
Classifier: License :: OSI Approved :: BSD License
Classifier: Operating System :: OS Independent
Classifier: Programming Language :: Python
Classifier: Topic :: Internet :: WWW/HTTP :: Dynamic Content
Classifier: Topic :: Software Development :: Libraries :: Python Modules
Requires-Dist: ansible (<3,>=2)
Requires-Dist: boto (<3,>=2.4.6)
Requires-Dist: troposphere (<2.7,>=2.6)
Requires-Dist: click
Requires-Dist: py3-pilo
Requires-Dist: virtualenv
Requires-Dist: virtualenv-relocate
Provides-Extra: tests
Requires-Dist: mock (<2.0,>=1.0) ; extra == 'tests'
Requires-Dist: pytest (<3,>=2.5.2) ; extra == 'tests'
Requires-Dist: pytest-cov (<2,>=1.7) ; extra == 'tests'
